<?xml version='1.0' encoding='UTF-8'?>
<package version="0.0.5" uuid="alduino">
 <names>
  <name lang="en_US">ALDuino</name>
 </names>
 <descriptions>
  <description lang="en_US">NAOqi service to inteface with the Arduino microcontroller.</description>
 </descriptions>
 <supportedLanguages>
  <language>en_US</language>
 </supportedLanguages>
 <descriptionLanguages>
  <language>en_US</language>
 </descriptionLanguages>
 <contents/>
 <services>
  <service autorun="true" name="ALDuino" execStart="/usr/bin/python2 lib/register.py"/>
 </services>
</package>
